MANIFEST.in
setup.cfg
setup.py
mezzanine_instagram/__init__.py
mezzanine_instagram/admin.py
mezzanine_instagram/models.py
mezzanine_instagram/tests.py
mezzanine_instagram/urls.py
mezzanine_instagram/views.py
mezzanine_instagram.egg-info/PKG-INFO
mezzanine_instagram.egg-info/SOURCES.txt
mezzanine_instagram.egg-info/dependency_links.txt
mezzanine_instagram.egg-info/entry_points.txt
mezzanine_instagram.egg-info/requires.txt
mezzanine_instagram.egg-info/top_level.txt
mezzanine_instagram/management/__init__.py
mezzanine_instagram/management/commands/__init__.py
mezzanine_instagram/management/commands/build_tags_stream.py
mezzanine_instagram/templatetags/__init__.py
mezzanine_instagram/templatetags/instagram_tags.py