Metadata-Version: 1.1
Name: mezzanine-instagram
Version: v0.0.1.dev1
Summary: Django app that integrates Mezzanine CMS with Instagram
Home-page: https://github.com/shurik/mezzanine_instagram
Author: Sasha Vladimirskiy
Author-email: sasha@butchershop.co
License: MIT
Keywords: django mezzanine cms instagram
Platform: UNKNOWN
Classifier: Development Status :: 3 - Alpha
Classifier: Intended Audience :: Developers
Classifier: Topic :: Internet :: WWW/HTTP :: Site Management
Classifier: License :: OSI Approved :: MIT License
Classifier: Programming Language :: Python :: 2.7
